{
  "$schema": "https://static.modelcontextprotocol.io/schemas/2025-12-11/server.schema.json",
  "name": "io.github.squidcode/timebook",
  "title": "Timebook",
  "description": "Track time on usetimebook.com - start/stop timers, log entries, list projects/clients.",
  "version": "0.2.0",
  "repository": {
    "url": "https://github.com/squidcode/timebook-cli",
    "source": "github"
  },
  "websiteUrl": "https://usetimebook.com",
  "icons": [
    {
      "src": "https://usetimebook.com/favicon.svg",
      "mimeType": "image/svg+xml",
      "sizes": ["any"]
    }
  ],
  "packages": [
    {
      "registryType": "npm",
      "identifier": "@squidcode/timebook",
      "version": "0.2.0",
      "transport": {
        "type": "stdio"
      },
      "runtimeArguments": [
        {
          "type": "positional",
          "value": "mcp"
        }
      ],
      "environmentVariables": [
        {
          "name": "TIMEBOOK_API_URL",
          "description": "Override the Timebook API base URL. Defaults to https://usetimebook.com.",
          "isRequired": false,
          "isSecret": false,
          "format": "string"
        },
        {
          "name": "TIMEBOOK_WEB_URL",
          "description": "Override the Timebook web URL used during `timebook login`. Defaults to https://usetimebook.com.",
          "isRequired": false,
          "isSecret": false,
          "format": "string"
        }
      ]
    }
  ]
}
